{"updatedAt":"2026-02-10T15:34:22.387Z","entity":"ABAL","year":2021,"trees":{"import":[{"id":"cat:aluminio","level":"category","name":"Alumínio","metrics":{"fob":3166832273,"kg":1157343594},"children":[{"id":"sub:aluminio:aluminio-primario-em-forma-bruta--composicao-quimica-pureza--formato-lingote-sow-t-bar-liquido-etc","level":"subcategory","name":"Alumínio primário em forma bruta > Composição química (pureza) > Formato (lingote; Sow; T-bar; líquido etc.)","metrics":{"fob":1054223222,"kg":415884584},"children":[{"id":"ncm:76011000","level":"ncm","name":"76011000","metrics":{"fob":1054223222,"kg":415884584},"meta":{"categoria":"Alumínio","subcategoria":"Alumínio primário em forma bruta > Composição química (pureza) > Formato (lingote; Sow; T-bar; líquido etc.)","ncm":"76011000"}}],"meta":{"categoria":"Alumínio","subcategoria":"Alumínio primário em forma bruta > Composição química (pureza) > Formato (lingote; Sow; T-bar; líquido etc.)"}},{"id":"sub:aluminio:ligas-de-aluminio--composicao-quimica--formato-lingote-tarugo-liquido-etc","level":"subcategory","name":"Ligas de alumínio > Composição química > Formato (lingote; tarugo; líquido etc.)","metrics":{"fob":433364034,"kg":170998058},"children":[{"id":"ncm:76012000","level":"ncm","name":"76012000","metrics":{"fob":433364034,"kg":170998058},"meta":{"categoria":"Alumínio","subcategoria":"Ligas de alumínio > Composição química > Formato (lingote; tarugo; líquido etc.)","ncm":"76012000"}}],"meta":{"categoria":"Alumínio","subcategoria":"Ligas de alumínio > Composição química > Formato (lingote; tarugo; líquido etc.)"}},{"id":"sub:aluminio:chapas-de-aluminio--formato-quadrado-retangular-etc--composicao-quimica-ligado-ou-nao-ligado","level":"subcategory","name":"Chapas de alumínio > Formato (quadrado; retangular etc.) > Composição química (ligado ou não ligado)","metrics":{"fob":277137955,"kg":101688132},"children":[{"id":"ncm:76061290","level":"ncm","name":"76061290","metrics":{"fob":158385774,"kg":58859156},"meta":{"categoria":"Alumínio","subcategoria":"Chapas de alumínio > Formato (quadrado; retangular etc.) > Composição química (ligado ou não ligado)","ncm":"76061290"}},{"id":"ncm:76061190","level":"ncm","name":"76061190","metrics":{"fob":39811545,"kg":20567869},"meta":{"categoria":"Alumínio","subcategoria":"Chapas de alumínio > Formato (quadrado; retangular etc.) > Composição química (ligado ou não ligado)","ncm":"76061190"}},{"id":"ncm:76061220","level":"ncm","name":"76061220","metrics":{"fob":25087825,"kg":7302609},"meta":{"categoria":"Alumínio","subcategoria":"Chapas de alumínio > Formato (quadrado; retangular etc.) > Composição química (ligado ou não ligado)","ncm":"76061220"}},{"id":"ncm:76069100","level":"ncm","name":"76069100","metrics":{"fob":17931692,"kg":5476559},"meta":{"categoria":"Alumínio","subcategoria":"Chapas de alumínio > Formato (quadrado; retangular etc.) > Composição química (ligado ou não ligado)","ncm":"76069100"}},{"id":"ncm:76069200","level":"ncm","name":"76069200","metrics":{"fob":17372012,"kg":5052085},"meta":{"categoria":"Alumínio","subcategoria":"Chapas de alumínio > Formato (quadrado; retangular etc.) > Composição química (ligado ou não ligado)","ncm":"76069200"}},{"id":"ncm:76061210","level":"ncm","name":"76061210","metrics":{"fob":15922513,"kg":3676047},"meta":{"categoria":"Alumínio","subcategoria":"Chapas de alumínio > Formato (quadrado; retangular etc.) > Composição química (ligado ou não ligado)","ncm":"76061210"}},{"id":"ncm:76061110","level":"ncm","name":"76061110","metrics":{"fob":2626594,"kg":753807},"meta":{"categoria":"Alumínio","subcategoria":"Chapas de alumínio > Formato (quadrado; retangular etc.) > Composição química (ligado ou não ligado)","ncm":"76061110"}}],"meta":{"categoria":"Alumínio","subcategoria":"Chapas de alumínio > Formato (quadrado; retangular etc.) > Composição química (ligado ou não ligado)"}},{"id":"sub:aluminio:desperdicios-e-residuos-e-sucata-de-aluminio","level":"subcategory","name":"Desperdícios e resíduos, e sucata, de alumínio","metrics":{"fob":243548022,"kg":146795158},"children":[{"id":"ncm:76020000","level":"ncm","name":"76020000","metrics":{"fob":243548022,"kg":146795158},"meta":{"categoria":"Alumínio","subcategoria":"Desperdícios e resíduos, e sucata, de alumínio","ncm":"76020000"}}],"meta":{"categoria":"Alumínio","subcategoria":"Desperdícios e resíduos, e sucata, de alumínio"}},{"id":"sub:aluminio:outras-obras-de-aluminio","level":"subcategory","name":"Outras obras de alumínio","metrics":{"fob":242219485,"kg":27366481},"children":[{"id":"ncm:76169900","level":"ncm","name":"76169900","metrics":{"fob":224045658,"kg":26357426},"meta":{"categoria":"Alumínio","subcategoria":"Outras obras de alumínio","ncm":"76169900"}},{"id":"ncm:76161000","level":"ncm","name":"76161000","metrics":{"fob":15189341,"kg":885967},"meta":{"categoria":"Alumínio","subcategoria":"Outras obras de alumínio","ncm":"76161000"}},{"id":"ncm:76169100","level":"ncm","name":"76169100","metrics":{"fob":2984486,"kg":123088},"meta":{"categoria":"Alumínio","subcategoria":"Outras obras de alumínio","ncm":"76169100"}}],"meta":{"categoria":"Alumínio","subcategoria":"Outras obras de alumínio"}},{"id":"sub:aluminio:folhas-de-aluminio--suporte-sem-ou-com","level":"subcategory","name":"Folhas de alumínio > Suporte (sem ou com)","metrics":{"fob":156336402,"kg":34794853},"children":[{"id":"ncm:76071190","level":"ncm","name":"76071190","metrics":{"fob":62231940,"kg":17720425},"meta":{"categoria":"Alumínio","subcategoria":"Folhas de alumínio > Suporte (sem ou com)","ncm":"76071190"}},{"id":"ncm:76071990","level":"ncm","name":"76071990","metrics":{"fob":47695324,"kg":7960384},"meta":{"categoria":"Alumínio","subcategoria":"Folhas de alumínio > Suporte (sem ou com)","ncm":"76071990"}},{"id":"ncm:76072000","level":"ncm","name":"76072000","metrics":{"fob":36374041,"kg":8126203},"meta":{"categoria":"Alumínio","subcategoria":"Folhas de alumínio > Suporte (sem ou com)","ncm":"76072000"}},{"id":"ncm:76071910","level":"ncm","name":"76071910","metrics":{"fob":7757207,"kg":363048},"meta":{"categoria":"Alumínio","subcategoria":"Folhas de alumínio > Suporte (sem ou com)","ncm":"76071910"}},{"id":"ncm:76071110","level":"ncm","name":"76071110","metrics":{"fob":2277890,"kg":624793},"meta":{"categoria":"Alumínio","subcategoria":"Folhas de alumínio > Suporte (sem ou com)","ncm":"76071110"}}],"meta":{"categoria":"Alumínio","subcategoria":"Folhas de alumínio > Suporte (sem ou com)"}},{"id":"sub:aluminio:automotivo--rodas-para-veiculos--de-aluminio","level":"subcategory","name":"Automotivo > Rodas para veículos > De alumínio","metrics":{"fob":150669700,"kg":34953886},"children":[{"id":"ncm:87087090","level":"ncm","name":"87087090","metrics":{"fob":150669700,"kg":34953886},"meta":{"categoria":"Alumínio","subcategoria":"Automotivo > Rodas para veículos > De alumínio","ncm":"87087090"}}],"meta":{"categoria":"Alumínio","subcategoria":"Automotivo > Rodas para veículos > De alumínio"}},{"id":"sub:aluminio:condutores-eletricos--cabos-revestidos--para-tensao-nao-superior-a-1000v--de-aluminio","level":"subcategory","name":"Condutores elétricos > Cabos revestidos > Para tensão não superior a 1000V > De alumínio","metrics":{"fob":139276868,"kg":14888871},"children":[{"id":"ncm:85444900","level":"ncm","name":"85444900","metrics":{"fob":139276868,"kg":14888871},"meta":{"categoria":"Alumínio","subcategoria":"Condutores elétricos > Cabos revestidos > Para tensão não superior a 1000V > De alumínio","ncm":"85444900"}}],"meta":{"categoria":"Alumínio","subcategoria":"Condutores elétricos > Cabos revestidos > Para tensão não superior a 1000V > De alumínio"}},{"id":"sub:aluminio:fios-de-aluminio--composicao-quimica-ligado-ou-nao-ligado--dimensao","level":"subcategory","name":"Fios de alumínio > Composição química (ligado ou não ligado) > Dimensão","metrics":{"fob":102328382,"kg":36638354},"children":[{"id":"ncm:76051110","level":"ncm","name":"76051110","metrics":{"fob":60015115,"kg":22798419},"meta":{"categoria":"Alumínio","subcategoria":"Fios de alumínio > Composição química (ligado ou não ligado) > Dimensão","ncm":"76051110"}},{"id":"ncm:76052990","level":"ncm","name":"76052990","metrics":{"fob":18020440,"kg":5095509},"meta":{"categoria":"Alumínio","subcategoria":"Fios de alumínio > Composição química (ligado ou não ligado) > Dimensão","ncm":"76052990"}},{"id":"ncm:76051190","level":"ncm","name":"76051190","metrics":{"fob":11814664,"kg":4537952},"meta":{"categoria":"Alumínio","subcategoria":"Fios de alumínio > Composição química (ligado ou não ligado) > Dimensão","ncm":"76051190"}},{"id":"ncm:76052190","level":"ncm","name":"76052190","metrics":{"fob":8621043,"kg":2810512},"meta":{"categoria":"Alumínio","subcategoria":"Fios de alumínio > Composição química (ligado ou não ligado) > Dimensão","ncm":"76052190"}},{"id":"ncm:76052110","level":"ncm","name":"76052110","metrics":{"fob":2096813,"kg":923083},"meta":{"categoria":"Alumínio","subcategoria":"Fios de alumínio > Composição química (ligado ou não ligado) > Dimensão","ncm":"76052110"}},{"id":"ncm:76051990","level":"ncm","name":"76051990","metrics":{"fob":912890,"kg":243648},"meta":{"categoria":"Alumínio","subcategoria":"Fios de alumínio > Composição química (ligado ou não ligado) > Dimensão","ncm":"76051990"}},{"id":"ncm:76051910","level":"ncm","name":"76051910","metrics":{"fob":744167,"kg":204731},"meta":{"categoria":"Alumínio","subcategoria":"Fios de alumínio > Composição química (ligado ou não ligado) > Dimensão","ncm":"76051910"}},{"id":"ncm:76052910","level":"ncm","name":"76052910","metrics":{"fob":103250,"kg":24500},"meta":{"categoria":"Alumínio","subcategoria":"Fios de alumínio > Composição química (ligado ou não ligado) > Dimensão","ncm":"76052910"}}],"meta":{"categoria":"Alumínio","subcategoria":"Fios de alumínio > Composição química (ligado ou não ligado) > Dimensão"}},{"id":"sub:aluminio:barras-de-aluminio--composicao-quimica-ligado-ou-nao-ligado","level":"subcategory","name":"Barras de alumínio > Composição química (ligado ou não ligado)","metrics":{"fob":53182604,"kg":13328578},"children":[{"id":"ncm:76042920","level":"ncm","name":"76042920","metrics":{"fob":26382037,"kg":7394743},"meta":{"categoria":"Alumínio","subcategoria":"Barras de alumínio > Composição química (ligado ou não ligado)","ncm":"76042920"}},{"id":"ncm:76042100","level":"ncm","name":"76042100","metrics":{"fob":13641338,"kg":3295675},"meta":{"categoria":"Alumínio","subcategoria":"Barras de alumínio > Composição química (ligado ou não ligado)","ncm":"76042100"}},{"id":"ncm:76042919","level":"ncm","name":"76042919","metrics":{"fob":9608836,"kg":1767070},"meta":{"categoria":"Alumínio","subcategoria":"Barras de alumínio > Composição química (ligado ou não ligado)","ncm":"76042919"}},{"id":"ncm:76041029","level":"ncm","name":"76041029","metrics":{"fob":1830356,"kg":416022},"meta":{"categoria":"Alumínio","subcategoria":"Barras de alumínio > Composição química (ligado ou não ligado)","ncm":"76041029"}},{"id":"ncm:76041021","level":"ncm","name":"76041021","metrics":{"fob":1555794,"kg":432479},"meta":{"categoria":"Alumínio","subcategoria":"Barras de alumínio > Composição química (ligado ou não ligado)","ncm":"76041021"}},{"id":"ncm:76041010","level":"ncm","name":"76041010","metrics":{"fob":159518,"kg":22017},"meta":{"categoria":"Alumínio","subcategoria":"Barras de alumínio > Composição química (ligado ou não ligado)","ncm":"76041010"}},{"id":"ncm:76042911","level":"ncm","name":"76042911","metrics":{"fob":4725,"kg":572},"meta":{"categoria":"Alumínio","subcategoria":"Barras de alumínio > Composição química (ligado ou não ligado)","ncm":"76042911"}}],"meta":{"categoria":"Alumínio","subcategoria":"Barras de alumínio > Composição química (ligado ou não ligado)"}},{"id":"sub:aluminio:condutores-eletricos--cabos-revestidos--para-tensao-superior-a-1000v--de-aluminio","level":"subcategory","name":"Condutores elétricos > Cabos revestidos > Para tensão superior a 1000V > De alumínio","metrics":{"fob":51883373,"kg":7342314},"children":[{"id":"ncm:85446000","level":"ncm","name":"85446000","metrics":{"fob":51883373,"kg":7342314},"meta":{"categoria":"Alumínio","subcategoria":"Condutores elétricos > Cabos revestidos > Para tensão superior a 1000V > De alumínio","ncm":"85446000"}}],"meta":{"categoria":"Alumínio","subcategoria":"Condutores elétricos > Cabos revestidos > Para tensão superior a 1000V > De alumínio"}},{"id":"sub:aluminio:recipientes-de-aluminio--capacidade-nao-superior-a-300-litros--outros-usos","level":"subcategory","name":"Recipientes de alumínio > Capacidade não superior a 300 litros > Outros usos","metrics":{"fob":45030740,"kg":5709881},"children":[{"id":"ncm:76129019","level":"ncm","name":"76129019","metrics":{"fob":32255621,"kg":4279065},"meta":{"categoria":"Alumínio","subcategoria":"Recipientes de alumínio > Capacidade não superior a 300 litros > Outros usos","ncm":"76129019"}},{"id":"ncm:76129011","level":"ncm","name":"76129011","metrics":{"fob":10485828,"kg":1271330},"meta":{"categoria":"Alumínio","subcategoria":"Recipientes de alumínio > Capacidade não superior a 300 litros > Outros usos","ncm":"76129011"}},{"id":"ncm:76129090","level":"ncm","name":"76129090","metrics":{"fob":1936347,"kg":146284},"meta":{"categoria":"Alumínio","subcategoria":"Recipientes de alumínio > Capacidade não superior a 300 litros > Outros usos","ncm":"76129090"}},{"id":"ncm:76129012","level":"ncm","name":"76129012","metrics":{"fob":352944,"kg":13202},"meta":{"categoria":"Alumínio","subcategoria":"Recipientes de alumínio > Capacidade não superior a 300 litros > Outros usos","ncm":"76129012"}}],"meta":{"categoria":"Alumínio","subcategoria":"Recipientes de alumínio > Capacidade não superior a 300 litros > Outros usos"}},{"id":"sub:aluminio:artigos-de-uso-domestico--aplicacao-cozinha-higiene-outros","level":"subcategory","name":"Artigos de uso doméstico > Aplicação (cozinha, higiene, outros)","metrics":{"fob":44129210,"kg":8477244},"children":[{"id":"ncm:76151000","level":"ncm","name":"76151000","metrics":{"fob":43796074,"kg":8420404},"meta":{"categoria":"Alumínio","subcategoria":"Artigos de uso doméstico > Aplicação (cozinha, higiene, outros)","ncm":"76151000"}},{"id":"ncm:76152000","level":"ncm","name":"76152000","metrics":{"fob":333136,"kg":56840},"meta":{"categoria":"Alumínio","subcategoria":"Artigos de uso doméstico > Aplicação (cozinha, higiene, outros)","ncm":"76152000"}}],"meta":{"categoria":"Alumínio","subcategoria":"Artigos de uso doméstico > Aplicação (cozinha, higiene, outros)"}},{"id":"sub:aluminio:tubo-de-aluminio--de-liga-de-aluminio--com-ou-sem-costura","level":"subcategory","name":"Tubo de alumínio > De liga de alumínio > Com ou sem costura","metrics":{"fob":28234095,"kg":4904910},"children":[{"id":"ncm:76082090","level":"ncm","name":"76082090","metrics":{"fob":28218383,"kg":4903361},"meta":{"categoria":"Alumínio","subcategoria":"Tubo de alumínio > De liga de alumínio > Com ou sem costura","ncm":"76082090"}},{"id":"ncm:76082010","level":"ncm","name":"76082010","metrics":{"fob":15712,"kg":1549},"meta":{"categoria":"Alumínio","subcategoria":"Tubo de alumínio > De liga de alumínio > Com ou sem costura","ncm":"76082010"}}],"meta":{"categoria":"Alumínio","subcategoria":"Tubo de alumínio > De liga de alumínio > Com ou sem costura"}},{"id":"sub:aluminio:oxido-de-aluminio--outros-oxidos-de-aluminio--outros-usos","level":"subcategory","name":"Óxido de alumínio > Outros óxidos de alumínio > Outros usos","metrics":{"fob":20106649,"kg":33712942},"children":[{"id":"ncm:28182090","level":"ncm","name":"28182090","metrics":{"fob":20106649,"kg":33712942},"meta":{"categoria":"Alumínio","subcategoria":"Óxido de alumínio > Outros óxidos de alumínio > Outros usos","ncm":"28182090"}}],"meta":{"categoria":"Alumínio","subcategoria":"Óxido de alumínio > Outros óxidos de alumínio > Outros usos"}},{"id":"sub:aluminio:condutores-eletricos--fios-para-bobinar--de-aluminio","level":"subcategory","name":"Condutores elétricos > Fios para bobinar > De alumínio","metrics":{"fob":19506729,"kg":4912192},"children":[{"id":"ncm:85441910","level":"ncm","name":"85441910","metrics":{"fob":19506729,"kg":4912192},"meta":{"categoria":"Alumínio","subcategoria":"Condutores elétricos > Fios para bobinar > De alumínio","ncm":"85441910"}}],"meta":{"categoria":"Alumínio","subcategoria":"Condutores elétricos > Fios para bobinar > De alumínio"}},{"id":"sub:aluminio:cordas-cabos-e-trancas-nao-isolados--com-alma-de-aco","level":"subcategory","name":"Cordas, cabos e tranças não isolados > Com alma de aço","metrics":{"fob":17805148,"kg":7711885},"children":[{"id":"ncm:76141010","level":"ncm","name":"76141010","metrics":{"fob":17803860,"kg":7711851},"meta":{"categoria":"Alumínio","subcategoria":"Cordas, cabos e tranças não isolados > Com alma de aço","ncm":"76141010"}},{"id":"ncm:76141090","level":"ncm","name":"76141090","metrics":{"fob":1288,"kg":34},"meta":{"categoria":"Alumínio","subcategoria":"Cordas, cabos e tranças não isolados > Com alma de aço","ncm":"76141090"}}],"meta":{"categoria":"Alumínio","subcategoria":"Cordas, cabos e tranças não isolados > Com alma de aço"}},{"id":"sub:aluminio:cordas-cabos-e-trancas-nao-isolados--outros","level":"subcategory","name":"Cordas, cabos e tranças não isolados > Outros","metrics":{"fob":16877769,"kg":6780927},"children":[{"id":"ncm:76149010","level":"ncm","name":"76149010","metrics":{"fob":16786271,"kg":6764891},"meta":{"categoria":"Alumínio","subcategoria":"Cordas, cabos e tranças não isolados > Outros","ncm":"76149010"}},{"id":"ncm:76149090","level":"ncm","name":"76149090","metrics":{"fob":91498,"kg":16036},"meta":{"categoria":"Alumínio","subcategoria":"Cordas, cabos e tranças não isolados > Outros","ncm":"76149090"}}],"meta":{"categoria":"Alumínio","subcategoria":"Cordas, cabos e tranças não isolados > Outros"}},{"id":"sub:aluminio:construcoes-e-suas-partes--outros","level":"subcategory","name":"Construções e suas partes > Outros","metrics":{"fob":13952956,"kg":2586313},"children":[{"id":"ncm:76109000","level":"ncm","name":"76109000","metrics":{"fob":13952956,"kg":2586313},"meta":{"categoria":"Alumínio","subcategoria":"Construções e suas partes > Outros","ncm":"76109000"}}],"meta":{"categoria":"Alumínio","subcategoria":"Construções e suas partes > Outros"}},{"id":"sub:aluminio:acessorios-para-tubos-de-aluminio","level":"subcategory","name":"Acessórios para tubos de alumínio","metrics":{"fob":13278582,"kg":816643},"children":[{"id":"ncm:76090000","level":"ncm","name":"76090000","metrics":{"fob":13278582,"kg":816643},"meta":{"categoria":"Alumínio","subcategoria":"Acessórios para tubos de alumínio","ncm":"76090000"}}],"meta":{"categoria":"Alumínio","subcategoria":"Acessórios para tubos de alumínio"}},{"id":"sub:aluminio:oxido-de-aluminio--alumina-calcinada--usos-metalicos","level":"subcategory","name":"Óxido de alumínio > Alumina calcinada > Usos metálicos","metrics":{"fob":8557612,"kg":7136219},"children":[{"id":"ncm:28182010","level":"ncm","name":"28182010","metrics":{"fob":8557612,"kg":7136219},"meta":{"categoria":"Alumínio","subcategoria":"Óxido de alumínio > Alumina calcinada > Usos metálicos","ncm":"28182010"}}],"meta":{"categoria":"Alumínio","subcategoria":"Óxido de alumínio > Alumina calcinada > Usos metálicos"}},{"id":"sub:aluminio:hidroxido-de-aluminio","level":"subcategory","name":"Hidróxido de alumínio","metrics":{"fob":7762898,"kg":6828795},"children":[{"id":"ncm:28183000","level":"ncm","name":"28183000","metrics":{"fob":7762898,"kg":6828795},"meta":{"categoria":"Alumínio","subcategoria":"Hidróxido de alumínio","ncm":"28183000"}}],"meta":{"categoria":"Alumínio","subcategoria":"Hidróxido de alumínio"}},{"id":"sub:aluminio:pasta-de-aluminio","level":"subcategory","name":"Pasta de alumínio","metrics":{"fob":7264542,"kg":482197},"children":[{"id":"ncm:32129010","level":"ncm","name":"32129010","metrics":{"fob":7264542,"kg":482197},"meta":{"categoria":"Alumínio","subcategoria":"Pasta de alumínio","ncm":"32129010"}}],"meta":{"categoria":"Alumínio","subcategoria":"Pasta de alumínio"}},{"id":"sub:aluminio:recipientes-para-gases-comprimidos-ou-liquefeitos","level":"subcategory","name":"Recipientes para gases comprimidos ou liquefeitos","metrics":{"fob":6196642,"kg":457152},"children":[{"id":"ncm:76130000","level":"ncm","name":"76130000","metrics":{"fob":6196642,"kg":457152},"meta":{"categoria":"Alumínio","subcategoria":"Recipientes para gases comprimidos ou liquefeitos","ncm":"76130000"}}],"meta":{"categoria":"Alumínio","subcategoria":"Recipientes para gases comprimidos ou liquefeitos"}},{"id":"sub:aluminio:bauxita--bauxita-calcinada","level":"subcategory","name":"Bauxita > Bauxita calcinada","metrics":{"fob":2918674,"kg":6135908},"children":[{"id":"ncm:26060012","level":"ncm","name":"26060012","metrics":{"fob":2918674,"kg":6135908},"meta":{"categoria":"Alumínio","subcategoria":"Bauxita > Bauxita calcinada","ncm":"26060012"}}],"meta":{"categoria":"Alumínio","subcategoria":"Bauxita > Bauxita calcinada"}},{"id":"sub:aluminio:pos-e-escamas-de-aluminio--estrutura-lamelar-nao-lamelar","level":"subcategory","name":"Pós e escamas de alumínio > Estrutura (lamelar; não lamelar)","metrics":{"fob":2822114,"kg":536725},"children":[{"id":"ncm:76031000","level":"ncm","name":"76031000","metrics":{"fob":2264359,"kg":518463},"meta":{"categoria":"Alumínio","subcategoria":"Pós e escamas de alumínio > Estrutura (lamelar; não lamelar)","ncm":"76031000"}},{"id":"ncm:76032000","level":"ncm","name":"76032000","metrics":{"fob":557755,"kg":18262},"meta":{"categoria":"Alumínio","subcategoria":"Pós e escamas de alumínio > Estrutura (lamelar; não lamelar)","ncm":"76032000"}}],"meta":{"categoria":"Alumínio","subcategoria":"Pós e escamas de alumínio > Estrutura (lamelar; não lamelar)"}},{"id":"sub:aluminio:recipientes-de-aluminio--capacidade-nao-superior-a-300-litros--recipientes-tubulares-flexiveis","level":"subcategory","name":"Recipientes de alumínio > Capacidade não superior a 300 litros > Recipientes tubulares flexíveis","metrics":{"fob":2759158,"kg":323719},"children":[{"id":"ncm:76121000","level":"ncm","name":"76121000","metrics":{"fob":2759158,"kg":323719},"meta":{"categoria":"Alumínio","subcategoria":"Recipientes de alumínio > Capacidade não superior a 300 litros > Recipientes tubulares flexíveis","ncm":"76121000"}}],"meta":{"categoria":"Alumínio","subcategoria":"Recipientes de alumínio > Capacidade não superior a 300 litros > Recipientes tubulares flexíveis"}},{"id":"sub:aluminio:construcoes-e-suas-partes--portas-e-janelas-e-seus-caixilhos-alizares-e-soleiras","level":"subcategory","name":"Construções e suas partes > Portas e janelas, e seus caixilhos, alizares e soleiras","metrics":{"fob":1983454,"kg":265667},"children":[{"id":"ncm:76101000","level":"ncm","name":"76101000","metrics":{"fob":1983454,"kg":265667},"meta":{"categoria":"Alumínio","subcategoria":"Construções e suas partes > Portas e janelas, e seus caixilhos, alizares e soleiras","ncm":"76101000"}}],"meta":{"categoria":"Alumínio","subcategoria":"Construções e suas partes > Portas e janelas, e seus caixilhos, alizares e soleiras"}},{"id":"sub:aluminio:bauxita--bauxita-nao-calcinada","level":"subcategory","name":"Bauxita > Bauxita não calcinada","metrics":{"fob":1808021,"kg":54597000},"children":[{"id":"ncm:26060011","level":"ncm","name":"26060011","metrics":{"fob":1808021,"kg":54597000},"meta":{"categoria":"Alumínio","subcategoria":"Bauxita > Bauxita não calcinada","ncm":"26060011"}}],"meta":{"categoria":"Alumínio","subcategoria":"Bauxita > Bauxita não calcinada"}},{"id":"sub:aluminio:tubo-de-aluminio--nao-ligado","level":"subcategory","name":"Tubo de alumínio > Não ligado","metrics":{"fob":1360020,"kg":274341},"children":[{"id":"ncm:76081000","level":"ncm","name":"76081000","metrics":{"fob":1360020,"kg":274341},"meta":{"categoria":"Alumínio","subcategoria":"Tubo de alumínio > Não ligado","ncm":"76081000"}}],"meta":{"categoria":"Alumínio","subcategoria":"Tubo de alumínio > Não ligado"}},{"id":"sub:aluminio:recipientes-de-aluminio--capacidade-superior-a-300-litros","level":"subcategory","name":"Recipientes de alumínio > Capacidade superior a 300 litros","metrics":{"fob":307109,"kg":13665},"children":[{"id":"ncm:76110000","level":"ncm","name":"76110000","metrics":{"fob":307109,"kg":13665},"meta":{"categoria":"Alumínio","subcategoria":"Recipientes de alumínio > Capacidade superior a 300 litros","ncm":"76110000"}}],"meta":{"categoria":"Alumínio","subcategoria":"Recipientes de alumínio > Capacidade superior a 300 litros"}},{"id":"sub:aluminio:outros-minerio-de-aluminio--outros","level":"subcategory","name":"Outros minério de alumínio > Outros","metrics":{"fob":104,"kg":0},"children":[{"id":"ncm:26060090","level":"ncm","name":"26060090","metrics":{"fob":104,"kg":0},"meta":{"categoria":"Alumínio","subcategoria":"Outros minério de alumínio > Outros","ncm":"26060090"}}],"meta":{"categoria":"Alumínio","subcategoria":"Outros minério de alumínio > Outros"}}],"meta":{"categoria":"Alumínio"}}],"export":[{"id":"cat:aluminio","level":"category","name":"Alumínio","metrics":{"fob":4680303446,"kg":15461250077},"children":[{"id":"sub:aluminio:oxido-de-aluminio--alumina-calcinada--usos-metalicos","level":"subcategory","name":"Óxido de alumínio > Alumina calcinada > Usos metálicos","metrics":{"fob":2867890054,"kg":9032354861},"children":[{"id":"ncm:28182010","level":"ncm","name":"28182010","metrics":{"fob":2867890054,"kg":9032354861},"meta":{"categoria":"Alumínio","subcategoria":"Óxido de alumínio > Alumina calcinada > Usos metálicos","ncm":"28182010"}}],"meta":{"categoria":"Alumínio","subcategoria":"Óxido de alumínio > Alumina calcinada > Usos metálicos"}},{"id":"sub:aluminio:aluminio-primario-em-forma-bruta--composicao-quimica-pureza--formato-lingote-sow-t-bar-liquido-etc","level":"subcategory","name":"Alumínio primário em forma bruta > Composição química (pureza) > Formato (lingote; Sow; T-bar; líquido etc.)","metrics":{"fob":414114751,"kg":180296249},"children":[{"id":"ncm:76011000","level":"ncm","name":"76011000","metrics":{"fob":414114751,"kg":180296249},"meta":{"categoria":"Alumínio","subcategoria":"Alumínio primário em forma bruta > Composição química (pureza) > Formato (lingote; Sow; T-bar; líquido etc.)","ncm":"76011000"}}],"meta":{"categoria":"Alumínio","subcategoria":"Alumínio primário em forma bruta > Composição química (pureza) > Formato (lingote; Sow; T-bar; líquido etc.)"}},{"id":"sub:aluminio:chapas-de-aluminio--formato-quadrado-retangular-etc--composicao-quimica-ligado-ou-nao-ligado","level":"subcategory","name":"Chapas de alumínio > Formato (quadrado; retangular etc.) > Composição química (ligado ou não ligado)","metrics":{"fob":165413398,"kg":49057509},"children":[{"id":"ncm:76061290","level":"ncm","name":"76061290","metrics":{"fob":160672568,"kg":47992190},"meta":{"categoria":"Alumínio","subcategoria":"Chapas de alumínio > Formato (quadrado; retangular etc.) > Composição química (ligado ou não ligado)","ncm":"76061290"}},{"id":"ncm:76061190","level":"ncm","name":"76061190","metrics":{"fob":2794046,"kg":685850},"meta":{"categoria":"Alumínio","subcategoria":"Chapas de alumínio > Formato (quadrado; retangular etc.) > Composição química (ligado ou não ligado)","ncm":"76061190"}},{"id":"ncm:76069100","level":"ncm","name":"76069100","metrics":{"fob":1013287,"kg":226482},"meta":{"categoria":"Alumínio","subcategoria":"Chapas de alumínio > Formato (quadrado; retangular etc.) > Composição química (ligado ou não ligado)","ncm":"76069100"}},{"id":"ncm:76069200","level":"ncm","name":"76069200","metrics":{"fob":677652,"kg":98059},"meta":{"categoria":"Alumínio","subcategoria":"Chapas de alumínio > Formato (quadrado; retangular etc.) > Composição química (ligado ou não ligado)","ncm":"76069200"}},{"id":"ncm:76061210","level":"ncm","name":"76061210","metrics":{"fob":255372,"kg":54926},"meta":{"categoria":"Alumínio","subcategoria":"Chapas de alumínio > Formato (quadrado; retangular etc.) > Composição química (ligado ou não ligado)","ncm":"76061210"}},{"id":"ncm:76061110","level":"ncm","name":"76061110","metrics":{"fob":473,"kg":2},"meta":{"categoria":"Alumínio","subcategoria":"Chapas de alumínio > Formato (quadrado; retangular etc.) > Composição química (ligado ou não ligado)","ncm":"76061110"}}],"meta":{"categoria":"Alumínio","subcategoria":"Chapas de alumínio > Formato (quadrado; retangular etc.) > Composição química (ligado ou não ligado)"}},{"id":"sub:aluminio:condutores-eletricos--cabos-revestidos--para-tensao-nao-superior-a-1000v--de-aluminio","level":"subcategory","name":"Condutores elétricos > Cabos revestidos > Para tensão não superior a 1000V > De alumínio","metrics":{"fob":157778082,"kg":19060744},"children":[{"id":"ncm:85444900","level":"ncm","name":"85444900","metrics":{"fob":157778082,"kg":19060744},"meta":{"categoria":"Alumínio","subcategoria":"Condutores elétricos > Cabos revestidos > Para tensão não superior a 1000V > De alumínio","ncm":"85444900"}}],"meta":{"categoria":"Alumínio","subcategoria":"Condutores elétricos > Cabos revestidos > Para tensão não superior a 1000V > De alumínio"}},{"id":"sub:aluminio:bauxita--bauxita-nao-calcinada","level":"subcategory","name":"Bauxita > Bauxita não calcinada","metrics":{"fob":143567010,"kg":5164573430},"children":[{"id":"ncm:26060011","level":"ncm","name":"26060011","metrics":{"fob":143567010,"kg":5164573430},"meta":{"categoria":"Alumínio","subcategoria":"Bauxita > Bauxita não calcinada","ncm":"26060011"}}],"meta":{"categoria":"Alumínio","subcategoria":"Bauxita > Bauxita não calcinada"}},{"id":"sub:aluminio:hidroxido-de-aluminio","level":"subcategory","name":"Hidróxido de alumínio","metrics":{"fob":133566336,"kg":718471908},"children":[{"id":"ncm:28183000","level":"ncm","name":"28183000","metrics":{"fob":133566336,"kg":718471908},"meta":{"categoria":"Alumínio","subcategoria":"Hidróxido de alumínio","ncm":"28183000"}}],"meta":{"categoria":"Alumínio","subcategoria":"Hidróxido de alumínio"}},{"id":"sub:aluminio:artigos-de-uso-domestico--aplicacao-cozinha-higiene-outros","level":"subcategory","name":"Artigos de uso doméstico > Aplicação (cozinha, higiene, outros)","metrics":{"fob":130369995,"kg":19102680},"children":[{"id":"ncm:76151000","level":"ncm","name":"76151000","metrics":{"fob":130069572,"kg":19086705},"meta":{"categoria":"Alumínio","subcategoria":"Artigos de uso doméstico > Aplicação (cozinha, higiene, outros)","ncm":"76151000"}},{"id":"ncm:76152000","level":"ncm","name":"76152000","metrics":{"fob":300423,"kg":15975},"meta":{"categoria":"Alumínio","subcategoria":"Artigos de uso doméstico > Aplicação (cozinha, higiene, outros)","ncm":"76152000"}}],"meta":{"categoria":"Alumínio","subcategoria":"Artigos de uso doméstico > Aplicação (cozinha, higiene, outros)"}},{"id":"sub:aluminio:ligas-de-aluminio--composicao-quimica--formato-lingote-tarugo-liquido-etc","level":"subcategory","name":"Ligas de alumínio > Composição química > Formato (lingote; tarugo; líquido etc.)","metrics":{"fob":129840021,"kg":43022215},"children":[{"id":"ncm:76012000","level":"ncm","name":"76012000","metrics":{"fob":129840021,"kg":43022215},"meta":{"categoria":"Alumínio","subcategoria":"Ligas de alumínio > Composição química > Formato (lingote; tarugo; líquido etc.)","ncm":"76012000"}}],"meta":{"categoria":"Alumínio","subcategoria":"Ligas de alumínio > Composição química > Formato (lingote; tarugo; líquido etc.)"}},{"id":"sub:aluminio:automotivo--rodas-para-veiculos--de-aluminio","level":"subcategory","name":"Automotivo > Rodas para veículos > De alumínio","metrics":{"fob":125347530,"kg":38047769},"children":[{"id":"ncm:87087090","level":"ncm","name":"87087090","metrics":{"fob":125347530,"kg":38047769},"meta":{"categoria":"Alumínio","subcategoria":"Automotivo > Rodas para veículos > De alumínio","ncm":"87087090"}}],"meta":{"categoria":"Alumínio","subcategoria":"Automotivo > Rodas para veículos > De alumínio"}},{"id":"sub:aluminio:recipientes-de-aluminio--capacidade-nao-superior-a-300-litros--outros-usos","level":"subcategory","name":"Recipientes de alumínio > Capacidade não superior a 300 litros > Outros usos","metrics":{"fob":108814001,"kg":15065357},"children":[{"id":"ncm:76129019","level":"ncm","name":"76129019","metrics":{"fob":108139037,"kg":15005274},"meta":{"categoria":"Alumínio","subcategoria":"Recipientes de alumínio > Capacidade não superior a 300 litros > Outros usos","ncm":"76129019"}},{"id":"ncm:76129011","level":"ncm","name":"76129011","metrics":{"fob":381192,"kg":47950},"meta":{"categoria":"Alumínio","subcategoria":"Recipientes de alumínio > Capacidade não superior a 300 litros > Outros usos","ncm":"76129011"}},{"id":"ncm:76129012","level":"ncm","name":"76129012","metrics":{"fob":264242,"kg":5768},"meta":{"categoria":"Alumínio","subcategoria":"Recipientes de alumínio > Capacidade não superior a 300 litros > Outros usos","ncm":"76129012"}},{"id":"ncm:76129090","level":"ncm","name":"76129090","metrics":{"fob":29530,"kg":6365},"meta":{"categoria":"Alumínio","subcategoria":"Recipientes de alumínio > Capacidade não superior a 300 litros > Outros usos","ncm":"76129090"}}],"meta":{"categoria":"Alumínio","subcategoria":"Recipientes de alumínio > Capacidade não superior a 300 litros > Outros usos"}},{"id":"sub:aluminio:folhas-de-aluminio--suporte-sem-ou-com","level":"subcategory","name":"Folhas de alumínio > Suporte (sem ou com)","metrics":{"fob":82317207,"kg":20313675},"children":[{"id":"ncm:76071190","level":"ncm","name":"76071190","metrics":{"fob":69750414,"kg":18008501},"meta":{"categoria":"Alumínio","subcategoria":"Folhas de alumínio > Suporte (sem ou com)","ncm":"76071190"}},{"id":"ncm:76072000","level":"ncm","name":"76072000","metrics":{"fob":9164130,"kg":1781873},"meta":{"categoria":"Alumínio","subcategoria":"Folhas de alumínio > Suporte (sem ou com)","ncm":"76072000"}},{"id":"ncm:76071990","level":"ncm","name":"76071990","metrics":{"fob":2472829,"kg":342721},"meta":{"categoria":"Alumínio","subcategoria":"Folhas de alumínio > Suporte (sem ou com)","ncm":"76071990"}},{"id":"ncm:76071110","level":"ncm","name":"76071110","metrics":{"fob":798103,"kg":158090},"meta":{"categoria":"Alumínio","subcategoria":"Folhas de alumínio > Suporte (sem ou com)","ncm":"76071110"}},{"id":"ncm:76071910","level":"ncm","name":"76071910","metrics":{"fob":131731,"kg":22490},"meta":{"categoria":"Alumínio","subcategoria":"Folhas de alumínio > Suporte (sem ou com)","ncm":"76071910"}}],"meta":{"categoria":"Alumínio","subcategoria":"Folhas de alumínio > Suporte (sem ou com)"}},{"id":"sub:aluminio:bauxita--bauxita-calcinada","level":"subcategory","name":"Bauxita > Bauxita calcinada","metrics":{"fob":40340640,"kg":117250969},"children":[{"id":"ncm:26060012","level":"ncm","name":"26060012","metrics":{"fob":40340640,"kg":117250969},"meta":{"categoria":"Alumínio","subcategoria":"Bauxita > Bauxita calcinada","ncm":"26060012"}}],"meta":{"categoria":"Alumínio","subcategoria":"Bauxita > Bauxita calcinada"}},{"id":"sub:aluminio:condutores-eletricos--cabos-revestidos--para-tensao-superior-a-1000v--de-aluminio","level":"subcategory","name":"Condutores elétricos > Cabos revestidos > Para tensão superior a 1000V > De alumínio","metrics":{"fob":35961012,"kg":5011781},"children":[{"id":"ncm:85446000","level":"ncm","name":"85446000","metrics":{"fob":35961012,"kg":5011781},"meta":{"categoria":"Alumínio","subcategoria":"Condutores elétricos > Cabos revestidos > Para tensão superior a 1000V > De alumínio","ncm":"85446000"}}],"meta":{"categoria":"Alumínio","subcategoria":"Condutores elétricos > Cabos revestidos > Para tensão superior a 1000V > De alumínio"}},{"id":"sub:aluminio:outras-obras-de-aluminio","level":"subcategory","name":"Outras obras de alumínio","metrics":{"fob":35190618,"kg":2555602},"children":[{"id":"ncm:76169900","level":"ncm","name":"76169900","metrics":{"fob":33190388,"kg":2500530},"meta":{"categoria":"Alumínio","subcategoria":"Outras obras de alumínio","ncm":"76169900"}},{"id":"ncm:76161000","level":"ncm","name":"76161000","metrics":{"fob":1920185,"kg":52198},"meta":{"categoria":"Alumínio","subcategoria":"Outras obras de alumínio","ncm":"76161000"}},{"id":"ncm:76169100","level":"ncm","name":"76169100","metrics":{"fob":80045,"kg":2874},"meta":{"categoria":"Alumínio","subcategoria":"Outras obras de alumínio","ncm":"76169100"}}],"meta":{"categoria":"Alumínio","subcategoria":"Outras obras de alumínio"}},{"id":"sub:aluminio:desperdicios-e-residuos-e-sucata-de-aluminio","level":"subcategory","name":"Desperdícios e resíduos, e sucata, de alumínio","metrics":{"fob":33885552,"kg":22384653},"children":[{"id":"ncm:76020000","level":"ncm","name":"76020000","metrics":{"fob":33885552,"kg":22384653},"meta":{"categoria":"Alumínio","subcategoria":"Desperdícios e resíduos, e sucata, de alumínio","ncm":"76020000"}}],"meta":{"categoria":"Alumínio","subcategoria":"Desperdícios e resíduos, e sucata, de alumínio"}},{"id":"sub:aluminio:barras-de-aluminio--composicao-quimica-ligado-ou-nao-ligado","level":"subcategory","name":"Barras de alumínio > Composição química (ligado ou não ligado)","metrics":{"fob":28076847,"kg":5460830},"children":[{"id":"ncm:76042920","level":"ncm","name":"76042920","metrics":{"fob":14240165,"kg":2627015},"meta":{"categoria":"Alumínio","subcategoria":"Barras de alumínio > Composição química (ligado ou não ligado)","ncm":"76042920"}},{"id":"ncm:76042919","level":"ncm","name":"76042919","metrics":{"fob":7111374,"kg":1612474},"meta":{"categoria":"Alumínio","subcategoria":"Barras de alumínio > Composição química (ligado ou não ligado)","ncm":"76042919"}},{"id":"ncm:76042100","level":"ncm","name":"76042100","metrics":{"fob":6181063,"kg":1163245},"meta":{"categoria":"Alumínio","subcategoria":"Barras de alumínio > Composição química (ligado ou não ligado)","ncm":"76042100"}},{"id":"ncm:76041029","level":"ncm","name":"76041029","metrics":{"fob":404804,"kg":42845},"meta":{"categoria":"Alumínio","subcategoria":"Barras de alumínio > Composição química (ligado ou não ligado)","ncm":"76041029"}},{"id":"ncm:76041010","level":"ncm","name":"76041010","metrics":{"fob":111455,"kg":11507},"meta":{"categoria":"Alumínio","subcategoria":"Barras de alumínio > Composição química (ligado ou não ligado)","ncm":"76041010"}},{"id":"ncm:76041021","level":"ncm","name":"76041021","metrics":{"fob":27986,"kg":3744},"meta":{"categoria":"Alumínio","subcategoria":"Barras de alumínio > Composição química (ligado ou não ligado)","ncm":"76041021"}}],"meta":{"categoria":"Alumínio","subcategoria":"Barras de alumínio > Composição química (ligado ou não ligado)"}},{"id":"sub:aluminio:fios-de-aluminio--composicao-quimica-ligado-ou-nao-ligado--dimensao","level":"subcategory","name":"Fios de alumínio > Composição química (ligado ou não ligado) > Dimensão","metrics":{"fob":15032900,"kg":4211838},"children":[{"id":"ncm:76051110","level":"ncm","name":"76051110","metrics":{"fob":7825593,"kg":2478096},"meta":{"categoria":"Alumínio","subcategoria":"Fios de alumínio > Composição química (ligado ou não ligado) > Dimensão","ncm":"76051110"}},{"id":"ncm:76052190","level":"ncm","name":"76052190","metrics":{"fob":6797489,"kg":1678882},"meta":{"categoria":"Alumínio","subcategoria":"Fios de alumínio > Composição química (ligado ou não ligado) > Dimensão","ncm":"76052190"}},{"id":"ncm:76052990","level":"ncm","name":"76052990","metrics":{"fob":324161,"kg":45964},"meta":{"categoria":"Alumínio","subcategoria":"Fios de alumínio > Composição química (ligado ou não ligado) > Dimensão","ncm":"76052990"}},{"id":"ncm:76051190","level":"ncm","name":"76051190","metrics":{"fob":32130,"kg":3952},"meta":{"categoria":"Alumínio","subcategoria":"Fios de alumínio > Composição química (ligado ou não ligado) > Dimensão","ncm":"76051190"}},{"id":"ncm:76052910","level":"ncm","name":"76052910","metrics":{"fob":31141,"kg":1977},"meta":{"categoria":"Alumínio","subcategoria":"Fios de alumínio > Composição química (ligado ou não ligado) > Dimensão","ncm":"76052910"}},{"id":"ncm:76051990","level":"ncm","name":"76051990","metrics":{"fob":22386,"kg":2967},"meta":{"categoria":"Alumínio","subcategoria":"Fios de alumínio > Composição química (ligado ou não ligado) > Dimensão","ncm":"76051990"}}],"meta":{"categoria":"Alumínio","subcategoria":"Fios de alumínio > Composição química (ligado ou não ligado) > Dimensão"}},{"id":"sub:aluminio:tubo-de-aluminio--de-liga-de-aluminio--com-ou-sem-costura","level":"subcategory","name":"Tubo de alumínio > De liga de alumínio > Com ou sem costura","metrics":{"fob":5721598,"kg":931601},"children":[{"id":"ncm:76082090","level":"ncm","name":"76082090","metrics":{"fob":5699236,"kg":929325},"meta":{"categoria":"Alumínio","subcategoria":"Tubo de alumínio > De liga de alumínio > Com ou sem costura","ncm":"76082090"}},{"id":"ncm:76082010","level":"ncm","name":"76082010","metrics":{"fob":22362,"kg":2276},"meta":{"categoria":"Alumínio","subcategoria":"Tubo de alumínio > De liga de alumínio > Com ou sem costura","ncm":"76082010"}}],"meta":{"categoria":"Alumínio","subcategoria":"Tubo de alumínio > De liga de alumínio > Com ou sem costura"}},{"id":"sub:aluminio:pasta-de-aluminio","level":"subcategory","name":"Pasta de alumínio","metrics":{"fob":4239306,"kg":984268},"children":[{"id":"ncm:32129010","level":"ncm","name":"32129010","metrics":{"fob":4239306,"kg":984268},"meta":{"categoria":"Alumínio","subcategoria":"Pasta de alumínio","ncm":"32129010"}}],"meta":{"categoria":"Alumínio","subcategoria":"Pasta de alumínio"}},{"id":"sub:aluminio:acessorios-para-tubos-de-aluminio","level":"subcategory","name":"Acessórios para tubos de alumínio","metrics":{"fob":3912831,"kg":250427},"children":[{"id":"ncm:76090000","level":"ncm","name":"76090000","metrics":{"fob":3912831,"kg":250427},"meta":{"categoria":"Alumínio","subcategoria":"Acessórios para tubos de alumínio","ncm":"76090000"}}],"meta":{"categoria":"Alumínio","subcategoria":"Acessórios para tubos de alumínio"}},{"id":"sub:aluminio:recipientes-de-aluminio--capacidade-nao-superior-a-300-litros--recipientes-tubulares-flexiveis","level":"subcategory","name":"Recipientes de alumínio > Capacidade não superior a 300 litros > Recipientes tubulares flexíveis","metrics":{"fob":3509095,"kg":196718},"children":[{"id":"ncm:76121000","level":"ncm","name":"76121000","metrics":{"fob":3509095,"kg":196718},"meta":{"categoria":"Alumínio","subcategoria":"Recipientes de alumínio > Capacidade não superior a 300 litros > Recipientes tubulares flexíveis","ncm":"76121000"}}],"meta":{"categoria":"Alumínio","subcategoria":"Recipientes de alumínio > Capacidade não superior a 300 litros > Recipientes tubulares flexíveis"}},{"id":"sub:aluminio:construcoes-e-suas-partes--portas-e-janelas-e-seus-caixilhos-alizares-e-soleiras","level":"subcategory","name":"Construções e suas partes > Portas e janelas, e seus caixilhos, alizares e soleiras","metrics":{"fob":3252014,"kg":408828},"children":[{"id":"ncm:76101000","level":"ncm","name":"76101000","metrics":{"fob":3252014,"kg":408828},"meta":{"categoria":"Alumínio","subcategoria":"Construções e suas partes > Portas e janelas, e seus caixilhos, alizares e soleiras","ncm":"76101000"}}],"meta":{"categoria":"Alumínio","subcategoria":"Construções e suas partes > Portas e janelas, e seus caixilhos, alizares e soleiras"}},{"id":"sub:aluminio:condutores-eletricos--fios-para-bobinar--de-aluminio","level":"subcategory","name":"Condutores elétricos > Fios para bobinar > De alumínio","metrics":{"fob":2714631,"kg":490460},"children":[{"id":"ncm:85441910","level":"ncm","name":"85441910","metrics":{"fob":2714631,"kg":490460},"meta":{"categoria":"Alumínio","subcategoria":"Condutores elétricos > Fios para bobinar > De alumínio","ncm":"85441910"}}],"meta":{"categoria":"Alumínio","subcategoria":"Condutores elétricos > Fios para bobinar > De alumínio"}},{"id":"sub:aluminio:tubo-de-aluminio--nao-ligado","level":"subcategory","name":"Tubo de alumínio > Não ligado","metrics":{"fob":2572237,"kg":546028},"children":[{"id":"ncm:76081000","level":"ncm","name":"76081000","metrics":{"fob":2572237,"kg":546028},"meta":{"categoria":"Alumínio","subcategoria":"Tubo de alumínio > Não ligado","ncm":"76081000"}}],"meta":{"categoria":"Alumínio","subcategoria":"Tubo de alumínio > Não ligado"}},{"id":"sub:aluminio:pos-e-escamas-de-aluminio--estrutura-lamelar-nao-lamelar","level":"subcategory","name":"Pós e escamas de alumínio > Estrutura (lamelar; não lamelar)","metrics":{"fob":2534937,"kg":432715},"children":[{"id":"ncm:76031000","level":"ncm","name":"76031000","metrics":{"fob":2001216,"kg":350821},"meta":{"categoria":"Alumínio","subcategoria":"Pós e escamas de alumínio > Estrutura (lamelar; não lamelar)","ncm":"76031000"}},{"id":"ncm:76032000","level":"ncm","name":"76032000","metrics":{"fob":533721,"kg":81894},"meta":{"categoria":"Alumínio","subcategoria":"Pós e escamas de alumínio > Estrutura (lamelar; não lamelar)","ncm":"76032000"}}],"meta":{"categoria":"Alumínio","subcategoria":"Pós e escamas de alumínio > Estrutura (lamelar; não lamelar)"}},{"id":"sub:aluminio:construcoes-e-suas-partes--outros","level":"subcategory","name":"Construções e suas partes > Outros","metrics":{"fob":1637797,"kg":118539},"children":[{"id":"ncm:76109000","level":"ncm","name":"76109000","metrics":{"fob":1637797,"kg":118539},"meta":{"categoria":"Alumínio","subcategoria":"Construções e suas partes > Outros","ncm":"76109000"}}],"meta":{"categoria":"Alumínio","subcategoria":"Construções e suas partes > Outros"}},{"id":"sub:aluminio:cordas-cabos-e-trancas-nao-isolados--outros","level":"subcategory","name":"Cordas, cabos e tranças não isolados > Outros","metrics":{"fob":972022,"kg":242278},"children":[{"id":"ncm:76149010","level":"ncm","name":"76149010","metrics":{"fob":958977,"kg":241069},"meta":{"categoria":"Alumínio","subcategoria":"Cordas, cabos e tranças não isolados > Outros","ncm":"76149010"}},{"id":"ncm:76149090","level":"ncm","name":"76149090","metrics":{"fob":13045,"kg":1209},"meta":{"categoria":"Alumínio","subcategoria":"Cordas, cabos e tranças não isolados > Outros","ncm":"76149090"}}],"meta":{"categoria":"Alumínio","subcategoria":"Cordas, cabos e tranças não isolados > Outros"}},{"id":"sub:aluminio:cordas-cabos-e-trancas-nao-isolados--com-alma-de-aco","level":"subcategory","name":"Cordas, cabos e tranças não isolados > Com alma de aço","metrics":{"fob":794466,"kg":239113},"children":[{"id":"ncm:76141010","level":"ncm","name":"76141010","metrics":{"fob":794466,"kg":239113},"meta":{"categoria":"Alumínio","subcategoria":"Cordas, cabos e tranças não isolados > Com alma de aço","ncm":"76141010"}}],"meta":{"categoria":"Alumínio","subcategoria":"Cordas, cabos e tranças não isolados > Com alma de aço"}},{"id":"sub:aluminio:recipientes-de-aluminio--capacidade-superior-a-300-litros","level":"subcategory","name":"Recipientes de alumínio > Capacidade superior a 300 litros","metrics":{"fob":581496,"kg":112265},"children":[{"id":"ncm:76110000","level":"ncm","name":"76110000","metrics":{"fob":581496,"kg":112265},"meta":{"categoria":"Alumínio","subcategoria":"Recipientes de alumínio > Capacidade superior a 300 litros","ncm":"76110000"}}],"meta":{"categoria":"Alumínio","subcategoria":"Recipientes de alumínio > Capacidade superior a 300 litros"}},{"id":"sub:aluminio:recipientes-para-gases-comprimidos-ou-liquefeitos","level":"subcategory","name":"Recipientes para gases comprimidos ou liquefeitos","metrics":{"fob":303739,"kg":26102},"children":[{"id":"ncm:76130000","level":"ncm","name":"76130000","metrics":{"fob":303739,"kg":26102},"meta":{"categoria":"Alumínio","subcategoria":"Recipientes para gases comprimidos ou liquefeitos","ncm":"76130000"}}],"meta":{"categoria":"Alumínio","subcategoria":"Recipientes para gases comprimidos ou liquefeitos"}},{"id":"sub:aluminio:oxido-de-aluminio--outros-oxidos-de-aluminio--outros-usos","level":"subcategory","name":"Óxido de alumínio > Outros óxidos de alumínio > Outros usos","metrics":{"fob":49706,"kg":28664},"children":[{"id":"ncm:28182090","level":"ncm","name":"28182090","metrics":{"fob":49706,"kg":28664},"meta":{"categoria":"Alumínio","subcategoria":"Óxido de alumínio > Outros óxidos de alumínio > Outros usos","ncm":"28182090"}}],"meta":{"categoria":"Alumínio","subcategoria":"Óxido de alumínio > Outros óxidos de alumínio > Outros usos"}},{"id":"sub:aluminio:outros-minerio-de-aluminio--outros","level":"subcategory","name":"Outros minério de alumínio > Outros","metrics":{"fob":1617,"kg":1},"children":[{"id":"ncm:26060090","level":"ncm","name":"26060090","metrics":{"fob":1617,"kg":1},"meta":{"categoria":"Alumínio","subcategoria":"Outros minério de alumínio > Outros","ncm":"26060090"}}],"meta":{"categoria":"Alumínio","subcategoria":"Outros minério de alumínio > Outros"}}],"meta":{"categoria":"Alumínio"}}]},"charts":{"importSeries":[{"year":2010,"fob":1477400474,"kg":402460933,"usdPerTon":3670.916486197183},{"year":2011,"fob":2066441935,"kg":671003858,"usdPerTon":3079.6275019330815},{"year":2012,"fob":0,"kg":0,"usdPerTon":0},{"year":2013,"fob":0,"kg":0,"usdPerTon":0},{"year":2014,"fob":0,"kg":0,"usdPerTon":0},{"year":2015,"fob":0,"kg":0,"usdPerTon":0},{"year":2016,"fob":0,"kg":0,"usdPerTon":0},{"year":2017,"fob":0,"kg":0,"usdPerTon":0},{"year":2018,"fob":2408354377,"kg":888676702,"usdPerTon":2710.045589785249},{"year":2019,"fob":2405704502,"kg":1193840878,"usdPerTon":2015.0964390080132},{"year":2020,"fob":2017229585,"kg":1231213516,"usdPerTon":1638.4076025689112},{"year":2021,"fob":3166832273,"kg":1157343594,"usdPerTon":2736.29394884783},{"year":2022,"fob":3007620494,"kg":846218226,"usdPerTon":3554.1901622903592},{"year":2023,"fob":2318824692,"kg":705550519,"usdPerTon":3286.5466462792015},{"year":2024,"fob":2624517924,"kg":756009155,"usdPerTon":3471.5425159104057},{"year":2025,"fob":2899392895,"kg":801508433,"usdPerTon":3617.420323511431}],"exportSeries":[{"year":2010,"fob":0,"kg":0,"usdPerTon":0},{"year":2011,"fob":0,"kg":0,"usdPerTon":0},{"year":2012,"fob":0,"kg":0,"usdPerTon":0},{"year":2013,"fob":0,"kg":0,"usdPerTon":0},{"year":2014,"fob":0,"kg":0,"usdPerTon":0},{"year":2015,"fob":0,"kg":0,"usdPerTon":0},{"year":2016,"fob":0,"kg":0,"usdPerTon":0},{"year":2017,"fob":0,"kg":0,"usdPerTon":0},{"year":2018,"fob":4177256394,"kg":15915902171,"usdPerTon":262.458034054223},{"year":2019,"fob":3934965671,"kg":15338255119,"usdPerTon":256.54584830354196},{"year":2020,"fob":3561531361,"kg":13629671466,"usdPerTon":261.30720537794656},{"year":2021,"fob":4680303446,"kg":15461250077,"usdPerTon":302.7118391262795},{"year":2022,"fob":5507545239,"kg":14200349988,"usdPerTon":387.8457392708031},{"year":2023,"fob":4868939941,"kg":13951752624,"usdPerTon":348.9841077474655},{"year":2024,"fob":5841174385,"kg":14348477262,"usdPerTon":407.0936781890828},{"year":2025,"fob":6023195697,"kg":15425303876,"usdPerTon":390.47501076276365}]}}